rusty_results/__init__.py
rusty_results/exceptions.py
rusty_results/prelude.py
rusty_results/py.typed
rusty_results-1.1.1.dist-info/LICENSE
rusty_results-1.1.1.dist-info/METADATA
rusty_results-1.1.1.dist-info/WHEEL
rusty_results-1.1.1.dist-info/top_level.txt
rusty_results-1.1.1.dist-info/RECORD
