Metadata-Version: 2.1
Name: rusty-results
Version: 1.1.1
Summary: Rust inspired Result and Option types
Home-page: https://github.com/danielSanchezQ/rusty_results
Author: Daniel Sanchez Quiros, Antonio Jose Checa Bustos
Author-email: sanchez.quiros.daniel@gmail.com, antonio.checa.bustos@gmail.com
Classifier: Programming Language :: Python :: 3
Classifier: Operating System :: OS Independent
Requires-Python: >=3.7
License-File: LICENSE
Provides-Extra: pydantic
Requires-Dist: pydantic ; extra == 'pydantic'
